{
  "EMP0_-qfva8": {
    "user_name": "Olivia Hutcherson",
    "user_url": "https://unsplash.com/@ohutcherson?utm_source=unsample&utm_medium=referral&utm_campaign=api-credit",
    "photo_url": "https://unsplash.com/photos/EMP0_-qfva8?utm_source=unsample&utm_medium=referral&utm_campaign=api-credit"
  },
  "0S99shNpQ_A": {
    "user_name": "Birgith Roosipuu",
    "user_url": "https://unsplash.com/@msbirgith?utm_source=unsample&utm_medium=referral&utm_campaign=api-credit",
    "photo_url": "https://unsplash.com/photos/0S99shNpQ_A?utm_source=unsample&utm_medium=referral&utm_campaign=api-credit"
  },
  "_z1LfoESWpw": {
    "user_name": "Ikaia Pal",
    "user_url": "https://unsplash.com/@ikaiapal?utm_source=unsample&utm_medium=referral&utm_campaign=api-credit",
    "photo_url": "https://unsplash.com/photos/_z1LfoESWpw?utm_source=unsample&utm_medium=referral&utm_campaign=api-credit"
  },
  "Lv2lW5ImegQ": {
    "user_name": "Good Faces",
    "user_url": "https://unsplash.com/@goodfacesclub?utm_source=unsample&utm_medium=referral&utm_campaign=api-credit",
    "photo_url": "https://unsplash.com/photos/Lv2lW5ImegQ?utm_source=unsample&utm_medium=referral&utm_campaign=api-credit"
  },
  "3DjzN8gXtsc": {
    "user_name": "Morgane Le Breton",
    "user_url": "https://unsplash.com/@morgane_lb?utm_source=unsample&utm_medium=referral&utm_campaign=api-credit",
    "photo_url": "https://unsplash.com/photos/3DjzN8gXtsc?utm_source=unsample&utm_medium=referral&utm_campaign=api-credit"
  },
  "R_tEh-jjGcI": {
    "user_name": "Martin Katler",
    "user_url": "https://unsplash.com/@martinkatler?utm_source=unsample&utm_medium=referral&utm_campaign=api-credit",
    "photo_url": "https://unsplash.com/photos/R_tEh-jjGcI?utm_source=unsample&utm_medium=referral&utm_campaign=api-credit"
  },
  "mFZCmiMcCLg": {
    "user_name": "Riccardo Gazzin",
    "user_url": "https://unsplash.com/@riccardogazzin?utm_source=unsample&utm_medium=referral&utm_campaign=api-credit",
    "photo_url": "https://unsplash.com/photos/mFZCmiMcCLg?utm_source=unsample&utm_medium=referral&utm_campaign=api-credit"
  },
  "MzFZOKhg3Wk": {
    "user_name": "Simona Sergi",
    "user_url": "https://unsplash.com/@i_am_simoesse?utm_source=unsample&utm_medium=referral&utm_campaign=api-credit",
    "photo_url": "https://unsplash.com/photos/MzFZOKhg3Wk?utm_source=unsample&utm_medium=referral&utm_campaign=api-credit"
  },
  "NoRFKo74d48": {
    "user_name": "Liam Shaw",
    "user_url": "https://unsplash.com/@churrbroskii?utm_source=unsample&utm_medium=referral&utm_campaign=api-credit",
    "photo_url": "https://unsplash.com/photos/NoRFKo74d48?utm_source=unsample&utm_medium=referral&utm_campaign=api-credit"
  },
  "7mahJDEmLEI": {
    "user_name": "Chrissa Giannakoudi",
    "user_url": "https://unsplash.com/@chrissiey?utm_source=unsample&utm_medium=referral&utm_campaign=api-credit",
    "photo_url": "https://unsplash.com/photos/7mahJDEmLEI?utm_source=unsample&utm_medium=referral&utm_campaign=api-credit"
  },
  "3SKU2WmLHeM": {
    "user_name": "Benn McGuinness",
    "user_url": "https://unsplash.com/@bennmcguinness?utm_source=unsample&utm_medium=referral&utm_campaign=api-credit",
    "photo_url": "https://unsplash.com/photos/3SKU2WmLHeM?utm_source=unsample&utm_medium=referral&utm_campaign=api-credit"
  },
  "JKgpivfBggg": {
    "user_name": "Bence Sandor Sztrecska",
    "user_url": "https://unsplash.com/@arpheus?utm_source=unsample&utm_medium=referral&utm_campaign=api-credit",
    "photo_url": "https://unsplash.com/photos/JKgpivfBggg?utm_source=unsample&utm_medium=referral&utm_campaign=api-credit"
  },
  "ENnqi2ec4YQ": {
    "user_name": "Martin Katler",
    "user_url": "https://unsplash.com/@martinkatler?utm_source=unsample&utm_medium=referral&utm_campaign=api-credit",
    "photo_url": "https://unsplash.com/photos/ENnqi2ec4YQ?utm_source=unsample&utm_medium=referral&utm_campaign=api-credit"
  },
  "ueetWzeowos": {
    "user_name": "Max Whitehead",
    "user_url": "https://unsplash.com/@maxwhtd?utm_source=unsample&utm_medium=referral&utm_campaign=api-credit",
    "photo_url": "https://unsplash.com/photos/ueetWzeowos?utm_source=unsample&utm_medium=referral&utm_campaign=api-credit"
  },
  "sADRBC-i2TE": {
    "user_name": "Joshua Lawrence",
    "user_url": "https://unsplash.com/@orangetiephotography?utm_source=unsample&utm_medium=referral&utm_campaign=api-credit",
    "photo_url": "https://unsplash.com/photos/sADRBC-i2TE?utm_source=unsample&utm_medium=referral&utm_campaign=api-credit"
  },
  "wHKylOTcRA0": {
    "user_name": "Mathieu Odin",
    "user_url": "https://unsplash.com/@odindesign?utm_source=unsample&utm_medium=referral&utm_campaign=api-credit",
    "photo_url": "https://unsplash.com/photos/wHKylOTcRA0?utm_source=unsample&utm_medium=referral&utm_campaign=api-credit"
  },
  "I2YADJj1wcc": {
    "user_name": "kevin turcios",
    "user_url": "https://unsplash.com/@kevin_turcios?utm_source=unsample&utm_medium=referral&utm_campaign=api-credit",
    "photo_url": "https://unsplash.com/photos/I2YADJj1wcc?utm_source=unsample&utm_medium=referral&utm_campaign=api-credit"
  },
  "XVvX8WPFHD0": {
    "user_name": "Aaron Burden",
    "user_url": "https://unsplash.com/@aaronburden?utm_source=unsample&utm_medium=referral&utm_campaign=api-credit",
    "photo_url": "https://unsplash.com/photos/XVvX8WPFHD0?utm_source=unsample&utm_medium=referral&utm_campaign=api-credit"
  },
  "An9b9Lw_E0o": {
    "user_name": "kevin turcios",
    "user_url": "https://unsplash.com/@kevin_turcios?utm_source=unsample&utm_medium=referral&utm_campaign=api-credit",
    "photo_url": "https://unsplash.com/photos/An9b9Lw_E0o?utm_source=unsample&utm_medium=referral&utm_campaign=api-credit"
  },
  "6_ytBxmlBKU": {
    "user_name": "@whoisbenjamin",
    "user_url": "https://unsplash.com/@whoisbenjamin?utm_source=unsample&utm_medium=referral&utm_campaign=api-credit",
    "photo_url": "https://unsplash.com/photos/6_ytBxmlBKU?utm_source=unsample&utm_medium=referral&utm_campaign=api-credit"
  },
  "R8CpHSi5wwE": {
    "user_name": "Simon Lohmann",
    "user_url": "https://unsplash.com/@slohmann?utm_source=unsample&utm_medium=referral&utm_campaign=api-credit",
    "photo_url": "https://unsplash.com/photos/R8CpHSi5wwE?utm_source=unsample&utm_medium=referral&utm_campaign=api-credit"
  },
  "aLQoqzEwRcs": {
    "user_name": "Victor Grabarczyk",
    "user_url": "https://unsplash.com/@qrupt?utm_source=unsample&utm_medium=referral&utm_campaign=api-credit",
    "photo_url": "https://unsplash.com/photos/aLQoqzEwRcs?utm_source=unsample&utm_medium=referral&utm_campaign=api-credit"
  },
  "vzEeVwUgTmI": {
    "user_name": "Adam Neumann",
    "user_url": "https://unsplash.com/@adamneumann?utm_source=unsample&utm_medium=referral&utm_campaign=api-credit",
    "photo_url": "https://unsplash.com/photos/vzEeVwUgTmI?utm_source=unsample&utm_medium=referral&utm_campaign=api-credit"
  },
  "pLI-G5j0Vlg": {
    "user_name": "Jack Church",
    "user_url": "https://unsplash.com/@jackchurch?utm_source=unsample&utm_medium=referral&utm_campaign=api-credit",
    "photo_url": "https://unsplash.com/photos/pLI-G5j0Vlg?utm_source=unsample&utm_medium=referral&utm_campaign=api-credit"
  },
  "EusqCAoRDgI": {
    "user_name": "Cade Prior",
    "user_url": "https://unsplash.com/@medicadetion?utm_source=unsample&utm_medium=referral&utm_campaign=api-credit",
    "photo_url": "https://unsplash.com/photos/EusqCAoRDgI?utm_source=unsample&utm_medium=referral&utm_campaign=api-credit"
  },
  "E1rNoh9X1V4": {
    "user_name": "Jason Yoder",
    "user_url": "https://unsplash.com/@jasonyoder?utm_source=unsample&utm_medium=referral&utm_campaign=api-credit",
    "photo_url": "https://unsplash.com/photos/E1rNoh9X1V4?utm_source=unsample&utm_medium=referral&utm_campaign=api-credit"
  },
  "3u15auy_ggQ": {
    "user_name": "Luis Morera",
    "user_url": "https://unsplash.com/@luismorerat?utm_source=unsample&utm_medium=referral&utm_campaign=api-credit",
    "photo_url": "https://unsplash.com/photos/3u15auy_ggQ?utm_source=unsample&utm_medium=referral&utm_campaign=api-credit"
  },
  "zI_ld7Seek8": {
    "user_name": "Michelle Gerlach",
    "user_url": "https://unsplash.com/@michelleredd?utm_source=unsample&utm_medium=referral&utm_campaign=api-credit",
    "photo_url": "https://unsplash.com/photos/zI_ld7Seek8?utm_source=unsample&utm_medium=referral&utm_campaign=api-credit"
  },
  "BSXi16M9yRA": {
    "user_name": "Mattia Astorino",
    "user_url": "https://unsplash.com/@equinusocio?utm_source=unsample&utm_medium=referral&utm_campaign=api-credit",
    "photo_url": "https://unsplash.com/photos/BSXi16M9yRA?utm_source=unsample&utm_medium=referral&utm_campaign=api-credit"
  },
  "KZMvT8mww00": {
    "user_name": "Tom Gainor",
    "user_url": "https://unsplash.com/@its_tgain?utm_source=unsample&utm_medium=referral&utm_campaign=api-credit",
    "photo_url": "https://unsplash.com/photos/KZMvT8mww00?utm_source=unsample&utm_medium=referral&utm_campaign=api-credit"
  }
}